README.md
setup.py
pulumi_oneandone/__init__.py
pulumi_oneandone/_inputs.py
pulumi_oneandone/_utilities.py
pulumi_oneandone/baremetal.py
pulumi_oneandone/block_storage.py
pulumi_oneandone/firewall_policy.py
pulumi_oneandone/get_instance_size.py
pulumi_oneandone/image.py
pulumi_oneandone/loadbalancer.py
pulumi_oneandone/monitoring_policy.py
pulumi_oneandone/outputs.py
pulumi_oneandone/private_network.py
pulumi_oneandone/provider.py
pulumi_oneandone/public_ip.py
pulumi_oneandone/pulumi-plugin.json
pulumi_oneandone/py.typed
pulumi_oneandone/server.py
pulumi_oneandone/shared_storage.py
pulumi_oneandone/ssh_key.py
pulumi_oneandone/vpn.py
pulumi_oneandone.egg-info/PKG-INFO
pulumi_oneandone.egg-info/SOURCES.txt
pulumi_oneandone.egg-info/dependency_links.txt
pulumi_oneandone.egg-info/not-zip-safe
pulumi_oneandone.egg-info/requires.txt
pulumi_oneandone.egg-info/top_level.txt
pulumi_oneandone/config/__init__.py
pulumi_oneandone/config/vars.py