Metadata-Version: 2.1
Name: pulumi-oneandone
Version: 0.0.2
Summary: A Pulumi package for creating and managing oneandone cloud resources.
Home-page: https://github.com/akshaychopra5207/pulumi-oneandone
License: Apache-2.0
Project-URL: Repository, https://github.com/akshaychopra5207/pulumi-oneandone
Keywords: pulumi oneandone category/cloud
Platform: UNKNOWN
